README.rst
basecommand.py
cli.py
client.py
colors.py
setup.py
utils.py
commands/__init__.py
commands/clear.py
commands/fetch.py
commands/projects.py
commands/set.py
commands/unset.py
gitlab_vars.egg-info/PKG-INFO
gitlab_vars.egg-info/SOURCES.txt
gitlab_vars.egg-info/dependency_links.txt
gitlab_vars.egg-info/entry_points.txt
gitlab_vars.egg-info/top_level.txt