Metadata-Version: 1.0
Name: gitlab-vars
Version: 0.1
Summary: Manage GitLab secret variables with CLI
Home-page: https://github.com/deniskrishna/gitlabvars
Author: various
Author-email: intrrpt@ya.ru
License: BSD
Platform: UNKNOWN
